Metadata-Version: 2.1
Name: robotframework-capturefast
Version: 1.5.0
Summary: Capturefast Bridge Library For Robocorp
Home-page: https://github.com/CaptureFastSupport/CaptureFastForRobocorpLibrary
Author: CaptureFast
Author-email: support@capturefast.com
License: UNKNOWN
Keywords: OCR,Capture,Document,Parser,RPA
Platform: UNKNOWN
Requires: robotframework
Requires: six
